opnmf/__init__.py
opnmf/_version.py
opnmf/logging.py
opnmf/model.py
opnmf/opnmf.py
opnmf/selection.py
opnmf-0.0.2.dist-info/AUTHORS.rst
opnmf-0.0.2.dist-info/LICENSE.md
opnmf-0.0.2.dist-info/METADATA
opnmf-0.0.2.dist-info/WHEEL
opnmf-0.0.2.dist-info/top_level.txt
opnmf-0.0.2.dist-info/RECORD
